hollosmodule.py
Hollos_Module-0.0.7.data/scripts/hollosmodule.py
Hollos_Module-0.0.7.dist-info/LICENSE
Hollos_Module-0.0.7.dist-info/METADATA
Hollos_Module-0.0.7.dist-info/WHEEL
Hollos_Module-0.0.7.dist-info/top_level.txt
Hollos_Module-0.0.7.dist-info/RECORD
