Metadata-Version: 2.1
Name: Hollos-Module
Version: 0.0.7
Home-page: https://github.com/DevHollo/Hollos-Module
Author: Hollo
Author-email: hollo1234567890e@gmail.com
License-File: LICENSE
Requires-Dist: sty ==1.0.6
Requires-Dist: requests ==2.31.0
Requires-Dist: getpass4 ==0.0.14.1
Requires-Dist: pillow ==10.2.0
Requires-Dist: qrcode ==7.4.2
